Workbook

Sheet Review
A1: Question ID | B1: Subject | C1: Unit | D1: Chapter | E1: Official requirement | F1: Outcome | G1: Atom/concept | H1: Question | I1: Options | J1: Correct answer | K1: Explanation | L1: Difficulty | M1: Source reference | N1: Current status | O1: Expert decision | P1: Corrected question | Q1: Corrected answer | R1: Expert comments | S1: Reviewer name | T1: Qualification | U1: Review date
A2: C10-2627-MATH-REQ001-DIAG-001 | B2: Mathematics | C2: Number Systems | D2: Real Numbers | E2: REQ_MATH_2026_001, REQ_MATH_2026_002, REQ_MATH_2026_003, REQ_MATH_2026_004 | F2: LO_M1.1.1 — Express composite numbers as products of prime factors and calculate HCF and LCM using prime factorization. | G2: Fundamental Theorem of Arithmetic | H2: Using prime factorisation, find the HCF of 96 and 404. | I2: A. 12 B. 4 C. 2 D. 8 | J2: 4 | K2: 96 = 2^5 x 3 and 404 = 2^2 x 101. The only common prime power is 2^2, so the HCF is 4. | L2: 2 | M2: Maths_SecP1X_2026-27.pdf Page 2 | N2: draft / unverified / REVIEW_PENDING
A3: C10-2627-MATH-REQ001-DIAG-002 | B3: Mathematics | C3: Number Systems | D3: Real Numbers | E3: REQ_MATH_2026_001, REQ_MATH_2026_002, REQ_MATH_2026_003, REQ_MATH_2026_004 | F3: LO_M1.1.1 — Express composite numbers as products of prime factors and calculate HCF and LCM using prime factorization. | G3: Fundamental Theorem of Arithmetic | H3: Using prime factorisation, find the LCM of 72 and 120. | I3: (constructed response) | J3: 360 | K3: 72 = 2^3 x 3^2 and 120 = 2^3 x 3 x 5. Taking the highest power of each prime gives 2^3 x 3^2 x 5 = 360. | L3: 2 | M3: Maths_SecP1X_2026-27.pdf Page 2 | N3: draft / unverified / REVIEW_PENDING
A4: C10-2627-MATH-REQ001-DIAG-003 | B4: Mathematics | C4: Number Systems | D4: Real Numbers | E4: REQ_MATH_2026_001, REQ_MATH_2026_002, REQ_MATH_2026_003, REQ_MATH_2026_004 | F4: LO_M1.1.1 — Express composite numbers as products of prime factors and calculate HCF and LCM using prime factorization. | G4: Fundamental Theorem of Arithmetic | H4: The HCF of 306 and 657 is 9. Find their LCM without factorising again. | I4: (constructed response) | J4: 22338 | K4: For two positive integers, HCF x LCM = product of the numbers, so LCM = (306 x 657) / 9 = 22338. | L4: 3 | M4: Maths_SecP1X_2026-27.pdf Page 2 | N4: draft / unverified / REVIEW_PENDING
A5: C10-2627-MATH-REQ001-DIAG-004 | B5: Mathematics | C5: Number Systems | D5: Real Numbers | E5: REQ_MATH_2026_001, REQ_MATH_2026_002, REQ_MATH_2026_003, REQ_MATH_2026_004 | F5: LO_M1.1.1 — Express composite numbers as products of prime factors and calculate HCF and LCM using prime factorization. | G5: Fundamental Theorem of Arithmetic | H5: A florist has 84 roses and 126 lilies. She wants to make identical bunches, each bunch holding only roses or only lilies, with every bunch containing the same number of flowers and no flower left over. What is the greatest number of flowers she can put in one bunch? | I5: (constructed response) | J5: 42 | K5: The bunch size must divide both 84 and 126, so it is their HCF. 84 = 2^2 x 3 x 7 and 126 = 2 x 3^2 x 7, giving HCF = 2 x 3 x 7 = 42. | L5: 3 | M5: Maths_SecP1X_2026-27.pdf Page 2 | N5: draft / unverified / REVIEW_PENDING
A6: C10-2627-MATH-REQ001-DIAG-005 | B6: Mathematics | C6: Number Systems | D6: Real Numbers | E6: REQ_MATH_2026_001, REQ_MATH_2026_002, REQ_MATH_2026_003, REQ_MATH_2026_004 | F6: LO_M1.1.1 — Express composite numbers as products of prime factors and calculate HCF and LCM using prime factorization. | G6: Fundamental Theorem of Arithmetic | H6: Assertion (A): For any two positive integers a and b, HCF(a, b) x LCM(a, b) = a x b. Reason (R): Every composite number has a unique prime factorisation apart from the order of the factors. Choose the correct option. | I6: A. Both A and R are true and R is the correct explanation of A. B. Both A and R are true but R is not the correct explanation of A. C. A is true but R is false. D. A is false but R is true. | J6: Both A and R are true and R is the correct explanation of A. | K6: Uniqueness of factorisation lets each prime be split between the HCF (lowest power) and the LCM (highest power), and the two powers add back to the power in the product. | L6: 2 | M6: Maths_SecP1X_2026-27.pdf Page 2 | N6: draft / unverified / REVIEW_PENDING
A7: C10-2627-MATH-REQ001-DIAG-006 | B7: Mathematics | C7: Number Systems | D7: Real Numbers | E7: REQ_MATH_2026_001, REQ_MATH_2026_002, REQ_MATH_2026_003, REQ_MATH_2026_004 | F7: LO_M1.1.1 — Express composite numbers as products of prime factors and calculate HCF and LCM using prime factorization. | G7: Fundamental Theorem of Arithmetic | H7: Prime factorisations: | Number | Factorisation | | A | 2^3 x 3 x 5 | | B | 2^2 x 3^2 x 5 | | C | 2^2 x 3 x 5^2 | Write the HCF and the LCM of A, B and C. | I7: (constructed response) | J7: HCF = 60, LCM = 1800 | K7: Lowest common powers give 2^2 x 3 x 5 = 60. Highest powers give 2^3 x 3^2 x 5^2 = 1800. | L7: 3 | M7: Maths_SecP1X_2026-27.pdf Page 2 | N7: draft / unverified / REVIEW_PENDING
A8: C10-2627-MATH-REQ001-DIAG-007 | B8: Mathematics | C8: Number Systems | D8: Real Numbers | E8: REQ_MATH_2026_001, REQ_MATH_2026_002, REQ_MATH_2026_003, REQ_MATH_2026_004 | F8: LO_M1.1.1 — Express composite numbers as products of prime factors and calculate HCF and LCM using prime factorization. | G8: Fundamental Theorem of Arithmetic | H8: Two LED strips flash at intervals of 18 seconds and 24 seconds. They flash together at 7:00:00 pm. After how many seconds do they next flash together? | I8: (constructed response) | J8: 72 | K8: They coincide after a time that is a multiple of both intervals, so the answer is LCM(18, 24) = 72 seconds. | L8: 3 | M8: Maths_SecP1X_2026-27.pdf Page 2 | N8: draft / unverified / REVIEW_PENDING
A9: C10-2627-MATH-REQ001-REASS-001 | B9: Mathematics | C9: Number Systems | D9: Real Numbers | E9: REQ_MATH_2026_001, REQ_MATH_2026_002, REQ_MATH_2026_003, REQ_MATH_2026_004 | F9: LO_M1.1.1 — Express composite numbers as products of prime factors and calculate HCF and LCM using prime factorization. | G9: Fundamental Theorem of Arithmetic | H9: Express 3825 as a product of its prime factors. | I9: (constructed response) | J9: 3^2 x 5^2 x 17 | K9: 3825 / 3 = 1275, / 3 = 425, / 5 = 85, / 5 = 17, which is prime. Hence 3825 = 3^2 x 5^2 x 17. | L9: 2 | M9: Maths_SecP1X_2026-27.pdf Page 2 | N9: draft / unverified / REVIEW_PENDING
A10: C10-2627-MATH-REQ001-REASS-002 | B10: Mathematics | C10: Number Systems | D10: Real Numbers | E10: REQ_MATH_2026_001, REQ_MATH_2026_002, REQ_MATH_2026_003, REQ_MATH_2026_004 | F10: LO_M1.1.1 — Express composite numbers as products of prime factors and calculate HCF and LCM using prime factorization. | G10: Fundamental Theorem of Arithmetic | H10: Find the LCM of 12, 15 and 21. | I10: A. 630 B. 105 C. 420 D. 210 | J10: 420 | K10: 12 = 2^2 x 3, 15 = 3 x 5, 21 = 3 x 7. Highest powers give 2^2 x 3 x 5 x 7 = 420. | L10: 2 | M10: Maths_SecP1X_2026-27.pdf Page 2 | N10: draft / unverified / REVIEW_PENDING
A11: C10-2627-MATH-REQ001-REASS-003 | B11: Mathematics | C11: Number Systems | D11: Real Numbers | E11: REQ_MATH_2026_001, REQ_MATH_2026_002, REQ_MATH_2026_003, REQ_MATH_2026_004 | F11: LO_M1.1.1 — Express composite numbers as products of prime factors and calculate HCF and LCM using prime factorization. | G11: Fundamental Theorem of Arithmetic | H11: Two athletes start together at the starting line of a circular track. One completes a lap in 250 seconds and the other in 300 seconds, and both keep a steady pace. After how many minutes do they stand together at the starting line again? | I11: (constructed response) | J11: 25 minutes | K11: They meet after LCM(250, 300) = 1500 seconds, which is 25 minutes. | L11: 3 | M11: Maths_SecP1X_2026-27.pdf Page 2 | N11: draft / unverified / REVIEW_PENDING
A12: C10-2627-MATH-REQ001-REASS-004 | B12: Mathematics | C12: Number Systems | D12: Real Numbers | E12: REQ_MATH_2026_001, REQ_MATH_2026_002, REQ_MATH_2026_003, REQ_MATH_2026_004 | F12: LO_M1.1.1 — Express composite numbers as products of prime factors and calculate HCF and LCM using prime factorization. | G12: Fundamental Theorem of Arithmetic | H12: What is the smallest positive number that is divisible by both 63 and 84? | I12: (constructed response) | J12: 252 | K12: The smallest such number is LCM(63, 84). 63 = 3^2 x 7 and 84 = 2^2 x 3 x 7, so the LCM is 2^2 x 3^2 x 7 = 252. | L12: 2 | M12: Maths_SecP1X_2026-27.pdf Page 2 | N12: draft / unverified / REVIEW_PENDING
A13: C10-2627-MATH-REQ001-REASS-005 | B13: Mathematics | C13: Number Systems | D13: Real Numbers | E13: REQ_MATH_2026_001, REQ_MATH_2026_002, REQ_MATH_2026_003, REQ_MATH_2026_004 | F13: LO_M1.1.1 — Express composite numbers as products of prime factors and calculate HCF and LCM using prime factorization. | G13: Fundamental Theorem of Arithmetic | H13: State whether the following is true or false, and justify in one line: If two positive integers p and q are co-prime, then LCM(p, q) = p x q. | I13: A. True B. False | J13: True | K13: Co-prime means HCF = 1, and since HCF x LCM = pq, the LCM equals pq. | L13: 2 | M13: Maths_SecP1X_2026-27.pdf Page 2 | N13: draft / unverified / REVIEW_PENDING
... A236: C10-2627-MATH-REQ038-REASS-010 | B236: Mathematics | C236: Statistics & Probability | D236: Probability | E236: REQ_MATH_2026_038 | F236: LO_M14.1.1 — Calculate theoretical probability of single and compound events. | G236: Classical Approach to Probability | H236: State whether the following is true or false, and justify in one line: Classical probability assumes that all outcomes of the experiment are equally likely. | I236: A. True B. False | J236: True | K236: The classical definition divides favourable outcomes by total outcomes, which is valid only when the outcomes are equally likely. | L236: 2 | M236: Maths_SecP1X_2026-27.pdf Page 5 | N236: draft / unverified / REVIEW_PENDING

Sheet Summary
A1: Mathematics — Class 10 CBSE 2026-27 draft review
A3: Total questions | B3: =COUNTA(Review!A2:A236)
A4: Approved | B4: =COUNTIF(Review!O2:O236,"APPROVE")
A5: Revise | B5: =COUNTIF(Review!O2:O236,"REVISE")
A6: Rejected | B6: =COUNTIF(Review!O2:O236,"REJECT")
A7: Undecided | B7: =B3-B4-B5-B6
A9: Unit | B9: Questions | C9: Approved | D9: Revise | E9: Rejected
A10: Algebra | B10: =COUNTIF(Review!C2:C236,A10) | C10: =COUNTIFS(Review!C2:C236,A10,Review!O2:O236,"APPROVE") | D10: =COUNTIFS(Review!C2:C236,A10,Review!O2:O236,"REVISE") | E10: =COUNTIFS(Review!C2:C236,A10,Review!O2:O236,"REJECT")
A11: Coordinate Geometry | B11: =COUNTIF(Review!C2:C236,A11) | C11: =COUNTIFS(Review!C2:C236,A11,Review!O2:O236,"APPROVE") | D11: =COUNTIFS(Review!C2:C236,A11,Review!O2:O236,"REVISE") | E11: =COUNTIFS(Review!C2:C236,A11,Review!O2:O236,"REJECT")
A12: Geometry | B12: =COUNTIF(Review!C2:C236,A12) | C12: =COUNTIFS(Review!C2:C236,A12,Review!O2:O236,"APPROVE") | D12: =COUNTIFS(Review!C2:C236,A12,Review!O2:O236,"REVISE") | E12: =COUNTIFS(Review!C2:C236,A12,Review!O2:O236,"REJECT")
A13: Mensuration | B13: =COUNTIF(Review!C2:C236,A13) | C13: =COUNTIFS(Review!C2:C236,A13,Review!O2:O236,"APPROVE") | D13: =COUNTIFS(Review!C2:C236,A13,Review!O2:O236,"REVISE") | E13: =COUNTIFS(Review!C2:C236,A13,Review!O2:O236,"REJECT")
A14: Number Systems | B14: =COUNTIF(Review!C2:C236,A14) | C14: =COUNTIFS(Review!C2:C236,A14,Review!O2:O236,"APPROVE") | D14: =COUNTIFS(Review!C2:C236,A14,Review!O2:O236,"REVISE") | E14: =COUNTIFS(Review!C2:C236,A14,Review!O2:O236,"REJECT")
A15: Statistics & Probability | B15: =COUNTIF(Review!C2:C236,A15) | C15: =COUNTIFS(Review!C2:C236,A15,Review!O2:O236,"APPROVE") | D15: =COUNTIFS(Review!C2:C236,A15,Review!O2:O236,"REVISE") | E15: =COUNTIFS(Review!C2:C236,A15,Review!O2:O236,"REJECT")
A16: Trigonometry | B16: =COUNTIF(Review!C2:C236,A16) | C16: =COUNTIFS(Review!C2:C236,A16,Review!O2:O236,"APPROVE") | D16: =COUNTIFS(Review!C2:C236,A16,Review!O2:O236,"REVISE") | E16: =COUNTIFS(Review!C2:C236,A16,Review!O2:O236,"REJECT")
